multi_docker_build/__init__.py
multi_docker_build/build_docker_images.py
multi_docker_build-0.7.3.dist-info/LICENSE.txt
multi_docker_build-0.7.3.dist-info/METADATA
multi_docker_build-0.7.3.dist-info/WHEEL
multi_docker_build-0.7.3.dist-info/entry_points.txt
multi_docker_build-0.7.3.dist-info/top_level.txt
multi_docker_build-0.7.3.dist-info/RECORD
