Metadata-Version: 2.1
Name: multi-docker-build
Version: 0.7.3
Summary: Automated building/tagging/pushing of multiple Docker images in succession
Home-page: https://github.com/mruffalo/multi-docker-build
Author: Matt Ruffalo
Author-email: matt.ruffalo@gmail.com
License: MIT
Keywords: docker automation
Classifier: Development Status :: 4 - Beta
Classifier: Intended Audience :: Developers
Classifier: Topic :: Software Development
Classifier: License :: OSI Approved :: MIT License
Classifier: Programming Language :: Python :: 3 :: Only
Classifier: Programming Language :: Python :: 3.6
Classifier: Programming Language :: Python :: 3.7
Classifier: Programming Language :: Python :: 3.8
Classifier: Programming Language :: Python :: 3.9
Requires-Python: >=3.6
License-File: LICENSE.txt
